{
    "name": "root",
    "metadata": {
        "timer_format_version": "0.1.0",
        "start_time_seconds": "1685936392",
        "python_version": "3.9.13 (tags/v3.9.13:6de2ca5, May 17 2022, 16:36:42) [MSC v.1929 64 bit (AMD64)]",
        "command_line_arguments": "C:\\ML Agents\\envs\\ml_agents\\Scripts\\mlagents-learn config\\SumoMagnemiteVis.yaml --run-id=SumoMagnemiteVisSimpleV5FullyConnected32 --force",
        "mlagents_version": "0.30.0",
        "mlagents_envs_version": "0.30.0",
        "communication_protocol_version": "1.5.0",
        "pytorch_version": "1.7.1+cu110",
        "numpy_version": "1.21.2",
        "end_time_seconds": "1685936396"
    },
    "total": 3.6469524000000004,
    "count": 1,
    "self": 0.004806700000000941,
    "children": {
        "run_training.setup": {
            "total": 0.1400349999999999,
            "count": 1,
            "self": 0.1400349999999999
        },
        "TrainerController.start_learning": {
            "total": 3.5021107,
            "count": 1,
            "self": 0.00041290000000016036,
            "children": {
                "TrainerController._reset_env": {
                    "total": 3.5016871,
                    "count": 1,
                    "self": 3.5016871
                },
                "trainer_threads": {
                    "total": 8.999999998593466e-07,
                    "count": 1,
                    "self": 8.999999998593466e-07
                },
                "TrainerController._save_models": {
                    "total": 9.799999999948739e-06,
                    "count": 1,
                    "self": 9.799999999948739e-06
                }
            }
        }
    }
}